psyneulink/__init__.py
psyneulink/_typing.py
psyneulink/_version.py
psyneulink/core/__init__.py
psyneulink/core/components/__init__.py
psyneulink/core/components/component.py
psyneulink/core/components/shellclasses.py
psyneulink/core/components/functions/__init__.py
psyneulink/core/components/functions/function.py
psyneulink/core/components/functions/userdefinedfunction.py
psyneulink/core/components/functions/nonstateful/__init__.py
psyneulink/core/components/functions/nonstateful/distributionfunctions.py
psyneulink/core/components/functions/nonstateful/fitfunctions.py
psyneulink/core/components/functions/nonstateful/learningfunctions.py
psyneulink/core/components/functions/nonstateful/objectivefunctions.py
psyneulink/core/components/functions/nonstateful/optimizationfunctions.py
psyneulink/core/components/functions/nonstateful/selectionfunctions.py
psyneulink/core/components/functions/nonstateful/timerfunctions.py
psyneulink/core/components/functions/nonstateful/transferfunctions.py
psyneulink/core/components/functions/nonstateful/transformfunctions.py
psyneulink/core/components/functions/stateful/__init__.py
psyneulink/core/components/functions/stateful/integratorfunctions.py
psyneulink/core/components/functions/stateful/memoryfunctions.py
psyneulink/core/components/functions/stateful/statefulfunction.py
psyneulink/core/components/mechanisms/__init__.py
psyneulink/core/components/mechanisms/mechanism.py
psyneulink/core/components/mechanisms/modulatory/__init__.py
psyneulink/core/components/mechanisms/modulatory/modulatorymechanism.py
psyneulink/core/components/mechanisms/modulatory/control/__init__.py
psyneulink/core/components/mechanisms/modulatory/control/controlmechanism.py
psyneulink/core/components/mechanisms/modulatory/control/defaultcontrolmechanism.py
psyneulink/core/components/mechanisms/modulatory/control/optimizationcontrolmechanism.py
psyneulink/core/components/mechanisms/modulatory/control/gating/__init__.py
psyneulink-0.18.0.0.dist-info/METADATA
psyneulink-0.18.0.0.dist-info/WHEEL
psyneulink-0.18.0.0.dist-info/top_level.txt
psyneulink-0.18.0.0.dist-info/RECORD
