Metadata-Version: 2.1
Name: psyneulink
Version: 0.18.0.0
Summary: A block modeling system for cognitive neuroscience
Home-page: https://github.com/PrincetonUniversity/PsyNeuLink
Author: Jonathan Cohen, Princeton University
Author-email: jdc@princeton.edu
License: Apache
Keywords: cognitive modeling
Classifier: Development Status :: 3 - Alpha
Classifier: Intended Audience :: Developers
Classifier: Topic :: Software Development :: Build Tools
Classifier: License :: OSI Approved :: Apache Software License
Classifier: Programming Language :: Python :: 3
Classifier: Programming Language :: Python :: 3.8
Classifier: Programming Language :: Python :: 3.9
Classifier: Programming Language :: Python :: 3.10
Classifier: Programming Language :: Python :: 3.11
Classifier: Programming Language :: Python :: 3.12
Classifier: Programming Language :: Python :: 3.13
Requires-Python: >=3.8
Requires-Dist: beartype <0.22.0
Requires-Dist: dill <0.4.1
Requires-Dist: fastkde <2.1.6,>=2.0.0
Requires-Dist: graph-scheduler <1.3.0,>=1.2.1
Requires-Dist: graphviz <0.22.0
Requires-Dist: grpcio <1.76.0
Requires-Dist: leabra-psyneulink <0.3.3
Requires-Dist: llvmlite <0.45
Requires-Dist: matplotlib <3.10.7,>=3.7.0
Requires-Dist: networkx <3.6
Requires-Dist: numpy <2.3.4,>=1.21.0
Requires-Dist: optuna <4.6.0
Requires-Dist: packaging <26.0
Requires-Dist: pandas <2.3.3
Requires-Dist: pillow <11.4.0
Requires-Dist: pint <0.26.0
Requires-Dist: protobuf <6.32.2,>=3.20.2
Requires-Dist: rich <10.13,>=10.2
Requires-Dist: scipy <1.17,>=1.7.3
Requires-Dist: toposort <1.11
Requires-Dist: psutil <=7.1.0
Requires-Dist: modeci-mdf <0.5,>=0.4.3 ; (platform_machine == "AMD64" or platform_machine == "x86_64" or platform_machine == "arm64" or platform_machine == "aarch64") and platform_python_implementation == "CPython" and implementation_name == "cpython"
Requires-Dist: torch <2.9.0,>=1.13.0 ; (platform_machine == "AMD64" or platform_machine == "x86_64" or platform_machine == "arm64" or platform_machine == "aarch64") and platform_python_implementation == "CPython" and implementation_name == "cpython"
Provides-Extra: cuda
Requires-Dist: pycuda <2026,>2018 ; extra == 'cuda'
Provides-Extra: dev
Requires-Dist: jupyter <1.1.2 ; extra == 'dev'
Requires-Dist: packaging <26.0 ; extra == 'dev'
Requires-Dist: pytest <8.4.3 ; extra == 'dev'
Requires-Dist: pytest-benchmark <5.1.1 ; extra == 'dev'
Requires-Dist: pytest-cov <7.0.1 ; extra == 'dev'
Requires-Dist: pytest-forked <1.7.0 ; extra == 'dev'
Requires-Dist: pytest-helpers-namespace <2021.12.30 ; extra == 'dev'
Requires-Dist: pytest-profiling <1.8.2 ; extra == 'dev'
Requires-Dist: pytest-pycodestyle <2.6.0 ; extra == 'dev'
Requires-Dist: pytest-pydocstyle <2.5.0 ; extra == 'dev'
Requires-Dist: pytest-xdist <3.9.0,>=3.2.0 ; extra == 'dev'
Provides-Extra: doc
Requires-Dist: psyneulink-sphinx-theme <1.2.8.0 ; extra == 'doc'
Requires-Dist: sphinx <8.2.4,>=5 ; extra == 'doc'
Requires-Dist: sphinx-autodoc-typehints <3.3.0 ; extra == 'doc'
Requires-Dist: standard-imghdr <3.14 ; (python_version >= "3.13") and extra == 'doc'
Provides-Extra: tutorial
Requires-Dist: graphviz <0.22.0 ; extra == 'tutorial'
Requires-Dist: jupyter <1.1.2 ; extra == 'tutorial'
Requires-Dist: matplotlib <3.10.7,>=3.7.0 ; extra == 'tutorial'
